{
  "name": "kinsa_ili",
  "type": "source",
  "scripts": [
    {
      "path": "ingest.R",
      "manual": false,
      "frequency": 0,
      "last_run": "2026-04-15 08:28:24",
      "run_time": 1.118,
      "last_status": {
        "log": "missing value where TRUE/FALSE needed",
        "success": false
      }
    }
  ],
  "checked": "2026-04-06 14:00:23",
  "check_results": {
    "data/kinsa_ili/standard/data.csv.gz": []
  },
  "standalone": false,
  "last_date": "2026-03-31",
  "standard_state": {
    "./data/kinsa_ili/measure_info.json": "9d4c6ed86f9b0674988119b83c847ac3",
    "./data/kinsa_ili/standard/data.csv.gz": "0f9a0555029d6909ac4e46c0b970eaf7"
  }
}
