{
  "name": "delphi_nhsn",
  "title": "Delphi Nhsn",
  "licence": {
    "url": "http://opendatacommons.org/licenses/pddl",
    "name": "Open Data Commons Public Domain",
    "version": "1.0",
    "id": "odc-pddl"
  },
  "resources": [
    {
      "bytes": 87831,
      "encoding": "ISO-8859-1",
      "md5": "2a7eca9d79b00db527588afc834e073f",
      "format": "csv",
      "name": "data.csv",
      "filename": "data.csv.gz",
      "versions": {
        "hash": [
          "9a9400b3b9cc959fa1d56bdb386ce90b82f153b2",
          "6379c40be3e5f2890b21091b00677304e7c3324c",
          "9e2458b4be952a110ecea3aa1a337a555d6dd638"
        ],
        "author": [
          "Weinberger <daniel.weinberger@yale.edu>",
          "weinbergerlab <dweinber@gmail.com>",
          "Weinberger <daniel.weinberger@yale.edu>"
        ],
        "date": [
          "Tue Aug 19 07:42:18 2025 -0400",
          "Tue Aug 12 17:15:32 2025 -0400",
          "Mon Aug 11 12:33:11 2025 -0400"
        ],
        "message": [
          "mostly updated data. Some epic endpoints failing on virus pipeline",
          "rerun respiratory bundle",
          "add delphi datasets"
        ]
      },
      "source": [
        {
          "name": "CMU Delphi",
          "url": "https://cmu-delphi.github.io/delphi-epidata/",
          "location": "COVIDcast > National Healthcare Safety Network Respiratory Hospitalizations",
          "location_url": "https://cmu-delphi.github.io/delphi-epidata/api/covidcast-signals/nhsn.html"
        }
      ],
      "ids": [
        {
          "variable": "geography"
        }
      ],
      "id_length": 2,
      "time": "time",
      "profile": "data-resource",
      "created": "2025-08-25 08:35:12.111918",
      "last_modified": "2025-08-25 08:35:12.111918",
      "row_count": 14991,
      "entity_count": 57,
      "schema": {
        "fields": [
          {
            "name": "geography",
            "duplicates": 14934,
            "time_range": [0, 262],
            "type": "string",
            "missing": 0,
            "table": {
              "00": 263,
              "01": 263,
              "02": 263,
              "04": 263,
              "05": 263,
              "06": 263,
              "08": 263,
              "09": 263,
              "10": 263,
              "11": 263,
              "12": 263,
              "13": 263,
              "15": 263,
              "16": 263,
              "17": 263,
              "18": 263,
              "19": 263,
              "20": 263,
              "21": 263,
              "22": 263,
              "23": 263,
              "24": 263,
              "25": 263,
              "26": 263,
              "27": 263,
              "28": 263,
              "29": 263,
              "30": 263,
              "31": 263,
              "32": 263,
              "33": 263,
              "34": 263,
              "35": 263,
              "36": 263,
              "37": 263,
              "38": 263,
              "39": 263,
              "40": 263,
              "41": 263,
              "42": 263,
              "44": 263,
              "45": 263,
              "46": 263,
              "47": 263,
              "48": 263,
              "49": 263,
              "50": 263,
              "51": 263,
              "53": 263,
              "54": 263,
              "55": 263,
              "56": 263,
              "60": 263,
              "66": 263,
              "69": 263,
              "72": 263,
              "78": 263
            }
          },
          {
            "name": "time",
            "duplicates": 14728,
            "time_range": [0, 262],
            "type": "string",
            "missing": 0,
            "table": {
              "2020-08-02": 57,
              "2020-08-09": 57,
              "2020-08-16": 57,
              "2020-08-23": 57,
              "2020-08-30": 57,
              "2020-09-06": 57,
              "2020-09-13": 57,
              "2020-09-20": 57,
              "2020-09-27": 57,
              "2020-10-04": 57,
              "2020-10-11": 57,
              "2020-10-18": 57,
              "2020-10-25": 57,
              "2020-11-01": 57,
              "2020-11-08": 57,
              "2020-11-15": 57,
              "2020-11-22": 57,
              "2020-11-29": 57,
              "2020-12-06": 57,
              "2020-12-13": 57,
              "2020-12-20": 57,
              "2020-12-27": 57,
              "2021-01-03": 57,
              "2021-01-10": 57,
              "2021-01-17": 57,
              "2021-01-24": 57,
              "2021-01-31": 57,
              "2021-02-07": 57,
              "2021-02-14": 57,
              "2021-02-21": 57,
              "2021-02-28": 57,
              "2021-03-07": 57,
              "2021-03-14": 57,
              "2021-03-21": 57,
              "2021-03-28": 57,
              "2021-04-04": 57,
              "2021-04-11": 57,
              "2021-04-18": 57,
              "2021-04-25": 57,
              "2021-05-02": 57,
              "2021-05-09": 57,
              "2021-05-16": 57,
              "2021-05-23": 57,
              "2021-05-30": 57,
              "2021-06-06": 57,
              "2021-06-13": 57,
              "2021-06-20": 57,
              "2021-06-27": 57,
              "2021-07-04": 57,
              "2021-07-11": 57,
              "2021-07-18": 57,
              "2021-07-25": 57,
              "2021-08-01": 57,
              "2021-08-08": 57,
              "2021-08-15": 57,
              "2021-08-22": 57,
              "2021-08-29": 57,
              "2021-09-05": 57,
              "2021-09-12": 57,
              "2021-09-19": 57,
              "2021-09-26": 57,
              "2021-10-03": 57,
              "2021-10-10": 57,
              "2021-10-17": 57,
              "2021-10-24": 57,
              "2021-10-31": 57,
              "2021-11-07": 57,
              "2021-11-14": 57,
              "2021-11-21": 57,
              "2021-11-28": 57,
              "2021-12-05": 57,
              "2021-12-12": 57,
              "2021-12-19": 57,
              "2021-12-26": 57,
              "2022-01-02": 57,
              "2022-01-09": 57,
              "2022-01-16": 57,
              "2022-01-23": 57,
              "2022-01-30": 57,
              "2022-02-06": 57,
              "2022-02-13": 57,
              "2022-02-20": 57,
              "2022-02-27": 57,
              "2022-03-06": 57,
              "2022-03-13": 57,
              "2022-03-20": 57,
              "2022-03-27": 57,
              "2022-04-03": 57,
              "2022-04-10": 57,
              "2022-04-17": 57,
              "2022-04-24": 57,
              "2022-05-01": 57,
              "2022-05-08": 57,
              "2022-05-15": 57,
              "2022-05-22": 57,
              "2022-05-29": 57,
              "2022-06-05": 57,
              "2022-06-12": 57,
              "2022-06-19": 57,
              "2022-06-26": 57,
              "2022-07-03": 57,
              "2022-07-10": 57,
              "2022-07-17": 57,
              "2022-07-24": 57,
              "2022-07-31": 57,
              "2022-08-07": 57,
              "2022-08-14": 57,
              "2022-08-21": 57,
              "2022-08-28": 57,
              "2022-09-04": 57,
              "2022-09-11": 57,
              "2022-09-18": 57,
              "2022-09-25": 57,
              "2022-10-02": 57,
              "2022-10-09": 57,
              "2022-10-16": 57,
              "2022-10-23": 57,
              "2022-10-30": 57,
              "2022-11-06": 57,
              "2022-11-13": 57,
              "2022-11-20": 57,
              "2022-11-27": 57,
              "2022-12-04": 57,
              "2022-12-11": 57,
              "2022-12-18": 57,
              "2022-12-25": 57,
              "2023-01-01": 57,
              "2023-01-08": 57,
              "2023-01-15": 57,
              "2023-01-22": 57,
              "2023-01-29": 57,
              "2023-02-05": 57,
              "2023-02-12": 57,
              "2023-02-19": 57,
              "2023-02-26": 57,
              "2023-03-05": 57,
              "2023-03-12": 57,
              "2023-03-19": 57,
              "2023-03-26": 57,
              "2023-04-02": 57,
              "2023-04-09": 57,
              "2023-04-16": 57,
              "2023-04-23": 57,
              "2023-04-30": 57,
              "2023-05-07": 57,
              "2023-05-14": 57,
              "2023-05-21": 57,
              "2023-05-28": 57,
              "2023-06-04": 57,
              "2023-06-11": 57,
              "2023-06-18": 57,
              "2023-06-25": 57,
              "2023-07-02": 57,
              "2023-07-09": 57,
              "2023-07-16": 57,
              "2023-07-23": 57,
              "2023-07-30": 57,
              "2023-08-06": 57,
              "2023-08-13": 57,
              "2023-08-20": 57,
              "2023-08-27": 57,
              "2023-09-03": 57,
              "2023-09-10": 57,
              "2023-09-17": 57,
              "2023-09-24": 57,
              "2023-10-01": 57,
              "2023-10-08": 57,
              "2023-10-15": 57,
              "2023-10-22": 57,
              "2023-10-29": 57,
              "2023-11-05": 57,
              "2023-11-12": 57,
              "2023-11-19": 57,
              "2023-11-26": 57,
              "2023-12-03": 57,
              "2023-12-10": 57,
              "2023-12-17": 57,
              "2023-12-24": 57,
              "2023-12-31": 57,
              "2024-01-07": 57,
              "2024-01-14": 57,
              "2024-01-21": 57,
              "2024-01-28": 57,
              "2024-02-04": 57,
              "2024-02-11": 57,
              "2024-02-18": 57,
              "2024-02-25": 57,
              "2024-03-03": 57,
              "2024-03-10": 57,
              "2024-03-17": 57,
              "2024-03-24": 57,
              "2024-03-31": 57,
              "2024-04-07": 57,
              "2024-04-14": 57,
              "2024-04-21": 57,
              "2024-04-28": 57,
              "2024-05-05": 57,
              "2024-05-12": 57,
              "2024-05-19": 57,
              "2024-05-26": 57,
              "2024-06-02": 57,
              "2024-06-09": 57,
              "2024-06-16": 57,
              "2024-06-23": 57,
              "2024-06-30": 57,
              "2024-07-07": 57,
              "2024-07-14": 57,
              "2024-07-21": 57,
              "2024-07-28": 57,
              "2024-08-04": 57,
              "2024-08-11": 57,
              "2024-08-18": 57,
              "2024-08-25": 57,
              "2024-09-01": 57,
              "2024-09-08": 57,
              "2024-09-15": 57,
              "2024-09-22": 57,
              "2024-09-29": 57,
              "2024-10-06": 57,
              "2024-10-13": 57,
              "2024-10-20": 57,
              "2024-10-27": 57,
              "2024-11-03": 57,
              "2024-11-10": 57,
              "2024-11-17": 57,
              "2024-11-24": 57,
              "2024-12-01": 57,
              "2024-12-08": 57,
              "2024-12-15": 57,
              "2024-12-22": 57,
              "2024-12-29": 57,
              "2025-01-05": 57,
              "2025-01-12": 57,
              "2025-01-19": 57,
              "2025-01-26": 57,
              "2025-02-02": 57,
              "2025-02-09": 57,
              "2025-02-16": 57,
              "2025-02-23": 57,
              "2025-03-02": 57,
              "2025-03-09": 57,
              "2025-03-16": 57,
              "2025-03-23": 57,
              "2025-03-30": 57,
              "2025-04-06": 57,
              "2025-04-13": 57,
              "2025-04-20": 57,
              "2025-04-27": 57,
              "2025-05-04": 57,
              "2025-05-11": 57,
              "2025-05-18": 57,
              "2025-05-25": 57,
              "2025-06-01": 57,
              "2025-06-08": 57,
              "2025-06-15": 57,
              "2025-06-22": 57,
              "2025-06-29": 57,
              "2025-07-06": 57,
              "2025-07-13": 57,
              "2025-07-20": 57,
              "2025-07-27": 57,
              "2025-08-03": 57,
              "2025-08-10": 57
            }
          },
          {
            "name": "delphi_nhsn_covid",
            "duplicates": 12304,
            "time_range": [0, 262],
            "type": "integer",
            "missing": 288,
            "mean": 1080.359927,
            "sd": 5685.211297,
            "min": 0,
            "max": 156121
          },
          {
            "name": "delphi_nhsn_flu",
            "duplicates": 13958,
            "time_range": [0, 262],
            "type": "integer",
            "missing": 786,
            "mean": 158.041675,
            "sd": 1325.26097,
            "min": 0,
            "max": 54272
          },
          {
            "name": "delphi_nhsn_rsv",
            "duplicates": 14563,
            "time_range": [165, 262],
            "type": "integer",
            "missing": 10683,
            "mean": 83.37883,
            "sd": 581.870828,
            "min": 0,
            "max": 15242
          }
        ]
      },
      "sha512": "27d9375e8e303b74a90118f0ae463573b25c69cbe3c74cbf357940450ff5cc1abb7938fb6ab2228beca9a70d31f9181dab0d64fa165f6652777e207a0ab23d8b"
    }
  ],
  "measure_info": {
    "delphi_nhsn_covid": {
      "id": "delphi_nhsn_covid",
      "short_name": "Number of COVID hospitalizations in the National Healthcare Safety Network ",
      "category": "respiratory",
      "long_description": "The National Healthcare Safety Network (NHSN) is the nation’s most widely used healthcare-associated infection tracking system. This dataset reports preliminary and finalized weekly hospital respiratory data and metrics aggregated to national and state/territory levels reported to the CDC’s National Health Safety Network (NHSN). Values are available for reference dates beginning August 2020. Data for reference dates beginning November 1, 2024 were reported during the current mandated reporting period. More information regarding the mandate beginning November 1, 2024, is available from the CDC For reference dates in May 2024, NHSN received data from 78% of US EDs. HHS collects data from state and territorial health departments about many, but not all, hospitals in the U.S. Notably excluded from this dataset are psychiatric and rehabilitation facilities,and religious non-medical facilities. Number of reporting hospitals is determined based on the NHSN unique hospital identifier and not aggregated to the CMS certification number (CCN). Only hospitals indicated as active reporters in NHSN are included. Between reference dates 2024-05-01 and 2024-10-31, reported hospitalizations may not be fully representative, since reporting was voluntary. See the missingness section for more information about voluntary and mandatory reporting periods. Data for RSV from the pre-October 31, 2024 voluntary reporting period is particularly low quality. Only a tiny fraction of hospitals reported RSV-associated admissions such that they are undercounted by a factor of perhaps 100. For historical RSV-associated admissions, see the CDC’s RSV-NET (not currently mirrored by Delphi). For earlier issue dates certain signals may not be available. The earliest issue date with all the current signals available is epiweek 202451",
      "measure_type": "Number",
      "unit": "Number",
      "time_resolution": "Week",
      "sources": [
        {
          "name": "CMU Delphi",
          "url": "https://cmu-delphi.github.io/delphi-epidata/",
          "location": "COVIDcast > National Healthcare Safety Network Respiratory Hospitalizations",
          "location_url": "https://cmu-delphi.github.io/delphi-epidata/api/covidcast-signals/nhsn.html"
        }
      ],
      "citations": []
    },
    "delphi_nhsn_flu": {
      "id": "delphi_nhsn_flu",
      "short_name": "Number of influenza hospitalizations in the National Healthcare Safety Network ",
      "category": "respiratory",
      "long_description": "The National Healthcare Safety Network (NHSN) is the nation’s most widely used healthcare-associated infection tracking system. This dataset reports preliminary and finalized weekly hospital respiratory data and metrics aggregated to national and state/territory levels reported to the CDC’s National Health Safety Network (NHSN). Values are available for reference dates beginning August 2020. Data for reference dates beginning November 1, 2024 were reported during the current mandated reporting period. More information regarding the mandate beginning November 1, 2024, is available from the CDC For reference dates in May 2024, NHSN received data from 78% of US EDs. HHS collects data from state and territorial health departments about many, but not all, hospitals in the U.S. Notably excluded from this dataset are psychiatric and rehabilitation facilities,and religious non-medical facilities. Number of reporting hospitals is determined based on the NHSN unique hospital identifier and not aggregated to the CMS certification number (CCN). Only hospitals indicated as active reporters in NHSN are included. Between reference dates 2024-05-01 and 2024-10-31, reported hospitalizations may not be fully representative, since reporting was voluntary. See the missingness section for more information about voluntary and mandatory reporting periods. Data for RSV from the pre-October 31, 2024 voluntary reporting period is particularly low quality. Only a tiny fraction of hospitals reported RSV-associated admissions such that they are undercounted by a factor of perhaps 100. For historical RSV-associated admissions, see the CDC’s RSV-NET (not currently mirrored by Delphi). For earlier issue dates certain signals may not be available. The earliest issue date with all the current signals available is epiweek 202451",
      "measure_type": "Number",
      "unit": "Number",
      "time_resolution": "Week",
      "sources": [
        {
          "name": "CMU Delphi",
          "url": "https://cmu-delphi.github.io/delphi-epidata/",
          "location": "COVIDcast > National Healthcare Safety Network Respiratory Hospitalizations",
          "location_url": "https://cmu-delphi.github.io/delphi-epidata/api/covidcast-signals/nhsn.html"
        }
      ],
      "citations": []
    },
    "delphi_nhsn_rsv": {
      "id": "delphi_nhsn_rsv",
      "short_name": "Number of RSV hospitalizations in the National Healthcare Safety Network ",
      "category": "respiratory",
      "long_description": "The National Healthcare Safety Network (NHSN) is the nation’s most widely used healthcare-associated infection tracking system. This dataset reports preliminary and finalized weekly hospital respiratory data and metrics aggregated to national and state/territory levels reported to the CDC’s National Health Safety Network (NHSN). Values are available for reference dates beginning August 2020. Data for reference dates beginning November 1, 2024 were reported during the current mandated reporting period. More information regarding the mandate beginning November 1, 2024, is available from the CDC For reference dates in May 2024, NHSN received data from 78% of US EDs. HHS collects data from state and territorial health departments about many, but not all, hospitals in the U.S. Notably excluded from this dataset are psychiatric and rehabilitation facilities,and religious non-medical facilities. Number of reporting hospitals is determined based on the NHSN unique hospital identifier and not aggregated to the CMS certification number (CCN). Only hospitals indicated as active reporters in NHSN are included. Between reference dates 2024-05-01 and 2024-10-31, reported hospitalizations may not be fully representative, since reporting was voluntary. See the missingness section for more information about voluntary and mandatory reporting periods. Data for RSV from the pre-October 31, 2024 voluntary reporting period is particularly low quality. Only a tiny fraction of hospitals reported RSV-associated admissions such that they are undercounted by a factor of perhaps 100. For historical RSV-associated admissions, see the CDC’s RSV-NET (not currently mirrored by Delphi). For earlier issue dates certain signals may not be available. The earliest issue date with all the current signals available is epiweek 202451",
      "measure_type": "Number",
      "unit": "Number",
      "time_resolution": "Week",
      "sources": [
        {
          "name": "CMU Delphi",
          "url": "https://cmu-delphi.github.io/delphi-epidata/",
          "location": "COVIDcast > National Healthcare Safety Network Respiratory Hospitalizations",
          "location_url": "https://cmu-delphi.github.io/delphi-epidata/api/covidcast-signals/nhsn.html"
        }
      ],
      "citations": []
    }
  }
}
