[
  {
    "file": "raw/staging/Cxx_DM_multipleA1c_State_BRFSSAge.csv",
    "md5": "f6f24dec88f0be777377ba31399ee1cb",
    "date_processed": "2025-10-13 08:37:47",
    "standard_name": "all_patients",
    "Session Title": "HbA1c 7.5+ and HbA1c 7.0+ and HbA1c 6.5+ and Number of Patients by Age in Years (Current) Range and State of Residence (U.S.)",
    "Session ID": "2748873",
    "Data Model": "Patients",
    "Population Base": "All Patients",
    "Population Criteria Filters: These criteria are a summary and do not fully reflect the content of the exported session.": "Base Patient",
    "Session Date Range": "1/1/2023 - 7/10/2025",
    "Export User": "Stephanie Perniciaro",
    "Date of Export": "8/11/2025"
  }
]
